gpt2_estimator/__init__.py
gpt2_estimator/ckpt_restore_hook.py
gpt2_estimator/gpt2_estimator_fn.py
gpt2_estimator/gpt2/__init__.py
gpt2_estimator/gpt2/gpt_2.py
gpt2_estimator/gpt2/src/__init__.py
gpt2_estimator/gpt2/src/accumulate.py
gpt2_estimator/gpt2/src/encoder.py
gpt2_estimator/gpt2/src/load_dataset.py
gpt2_estimator/gpt2/src/model.py
gpt2_estimator/gpt2/src/sample.py
gpt2_estimator/gpt2/src/txt_load_dataset.py
gpt2_estimator-0.1.0.dist-info/LICENSE
gpt2_estimator-0.1.0.dist-info/METADATA
gpt2_estimator-0.1.0.dist-info/WHEEL
gpt2_estimator-0.1.0.dist-info/top_level.txt
gpt2_estimator-0.1.0.dist-info/RECORD
