Metadata-Version: 2.1
Name: gpt2-estimator
Version: 0.1.0
Summary: GPT2 in estimator
Home-page: https://github.com/JayYip/gpt2-estimator
Author: MedicalQATeam
Author-email: junpang.yip@gmail.com
License: MIT
Platform: UNKNOWN
Classifier: Programming Language :: Python :: 3.6
Classifier: License :: OSI Approved :: MIT License
Classifier: Operating System :: OS Independent
Requires-Python: >=3.5.0
Requires-Dist: pandas
Requires-Dist: numpy
Requires-Dist: requests
Requires-Dist: regex
Requires-Dist: tqdm
Requires-Dist: protobuf
Requires-Dist: tensorflow-gpu (==2.0.0a0)
